flake8_expression_complexity/__init__.py
flake8_expression_complexity/checker.py
flake8_expression_complexity/utils/__init__.py
flake8_expression_complexity/utils/ast.py
flake8_expression_complexity/utils/complexity.py
flake8_expression_complexity/utils/django.py
flake8_expression_complexity/utils/iterables.py
flake8_expression_complexity-0.0.10.dist-info/LICENSE
flake8_expression_complexity-0.0.10.dist-info/METADATA
flake8_expression_complexity-0.0.10.dist-info/WHEEL
flake8_expression_complexity-0.0.10.dist-info/entry_points.txt
flake8_expression_complexity-0.0.10.dist-info/top_level.txt
flake8_expression_complexity-0.0.10.dist-info/RECORD
